<!-- Terraria (EUR) -->
<header>
	<data_address>0x5F6000</data_address>
	<processAppCodeAddress>0x10B000</processAppCodeAddress>
	<num>0x3</num>
	<text_end>0x160000</text_end>
	<processLinearOffset>0x400000</processLinearOffset>
	<processHookAddress>0x1085E0</processHookAddress>
	<data_size>0x0</data_size>
</header>
<map>
	<entry>
		<src>0x100000</src>
		<dst>0x8000</dst>
		<size>0x3f8000</size>
	</entry>
	<entry>
		<src>0x4f8000</src>
		<dst>-0xf0000</dst>
		<size>0xf0000</size>
	</entry>
	<entry>
		<src>0x5e8000</src>
		<dst>-0xfe000</dst>
		<size>0xe000</size>
	</entry>
</map>
